LICENSE.txt
MANIFEST.in
setup.py
gc_user_agents.egg-info/PKG-INFO
gc_user_agents.egg-info/SOURCES.txt
gc_user_agents.egg-info/dependency_links.txt
gc_user_agents.egg-info/not-zip-safe
gc_user_agents.egg-info/requires.txt
gc_user_agents.egg-info/top_level.txt
user_agents/__init__.py
user_agents/compat.py
user_agents/parsers.py
user_agents/tests.py