Metadata-Version: 1.1
Name: gc-user-agents
Version: 2.0.1
Summary: A library to identify devices (phones, tablets) and their capabilities by parsing (browser/HTTP) user agent strings
Home-page: https://github.com/selwin/python-user-agents
Author: Selwin Ong
Author-email: selwin.ong@gmail.com
License: MIT
Platform: UNKNOWN
Classifier: Development Status :: 5 - Production/Stable
Classifier: Environment :: Web Environment
Classifier: Intended Audience :: Developers
Classifier: License :: OSI Approved :: MIT License
Classifier: Operating System :: OS Independent
Classifier: Programming Language :: Python
Classifier: Programming Language :: Python :: 2
Classifier: Programming Language :: Python :: 2.7
Classifier: Programming Language :: Python :: 3
Classifier: Programming Language :: Python :: 3.3
Classifier: Programming Language :: Python :: 3.4
Classifier: Topic :: Internet :: WWW/HTTP
Classifier: Topic :: Software Development :: Libraries :: Python Modules
